{
    "keep": {
        "days": true,
        "amount": 30
    },
    "auditLog": "D:\\taha\\graduation_project\\logs\\.d324f7f0e862fe47d79e6666dbd4a8c968fe76dd-audit.json",
    "files": [
        {
            "date": 1745584926461,
            "name": "D:\\taha\\graduation_project\\logs\\logfile-2025-04-25.log",
            "hash": "3b38b866891635b86aea6825d8678dc85ab68f44ac14c3dbebde4d5a1afef67f"
        },
        {
            "date": 1745637703610,
            "name": "D:\\taha\\graduation_project\\logs\\logfile-2025-04-26.log",
            "hash": "28eac896dfd6325f1211e82645924180d555537fe107a48835d52fcae5346a94"
        }
    ],
    "hashType": "sha256"
}